api_governor/__init__.py
api_governor/__main__.py
api_governor/diff.py
api_governor/formatters.py
api_governor/governor.py
api_governor/models.py
api_governor/output.py
api_governor/parser.py
api_governor/plugins.py
api_governor/rules.py
api_governor-1.0.0.dist-info/METADATA
api_governor-1.0.0.dist-info/WHEEL
api_governor-1.0.0.dist-info/entry_points.txt
api_governor-1.0.0.dist-info/licenses/LICENSE
api_governor-1.0.0.dist-info/RECORD
