Metadata-Version: 2.4
Name: api-governor
Version: 1.0.0
Summary: API governance and breaking change detection for OpenAPI specs
Project-URL: Homepage, https://github.com/akz4ol/api-governance-skill
Project-URL: Documentation, https://github.com/akz4ol/api-governance-skill#readme
Project-URL: Repository, https://github.com/akz4ol/api-governance-skill
Project-URL: Issues, https://github.com/akz4ol/api-governance-skill/issues
Project-URL: Changelog, https://github.com/akz4ol/api-governance-skill/blob/main/CHANGELOG.md
Author: API Governance Skill Contributors
License-Expression: MIT
License-File: LICENSE
Keywords: api,breaking-changes,governance,linting,openapi,validation
Classifier: Development Status :: 4 - Beta
Classifier: Intended Audience :: Developers
Classifier: License :: OSI Approved :: MIT License
Classifier: Operating System :: OS Independent
Classifier: Programming Language :: Python :: 3
Classifier: Programming Language :: Python :: 3.10
Classifier: Programming Language :: Python :: 3.11
Classifier: Programming Language :: Python :: 3.12
Classifier: Topic :: Software Development :: Quality Assurance
Classifier: Topic :: Software Development :: Testing
Requires-Python: >=3.10
Requires-Dist: jsonschema>=4.0
Requires-Dist: pyyaml>=6.0
Provides-Extra: dev
Requires-Dist: mypy>=1.0; extra == 'dev'
Requires-Dist: pytest-cov>=4.0; extra == 'dev'
Requires-Dist: pytest>=7.0; extra == 'dev'
Requires-Dist: ruff>=0.1.0; extra == 'dev'
Requires-Dist: types-pyyaml; extra == 'dev'
